{
    "CancelSubscription": "/sub/:subscriptionId/billing/cancel",
    "CreateSubscription": "/create",
    "ListSubscriptions": "/",
    "Subscription" : "/sub/:subscriptionId",
    "Settings": "/sub/:subscriptionId/settings",
    "ListUsers": "/sub/:subscriptionId/users",
    "ChangePlan": "/sub/:subscriptionId/billing/plan",
    "ListInvoices": "/sub/:subscriptionId/billing",
    "ManagePaymentMethods": "/sub/:subscriptionId/billing/payment-method",
    "UpdateBillingDetails": "/sub/:subscriptionId/billing/billing-details"
}